setup.py
brkt_requests/__init__.py
brkt_requests/oauth_requests.py
brkt_sdk.egg-info/PKG-INFO
brkt_sdk.egg-info/SOURCES.txt
brkt_sdk.egg-info/dependency_links.txt
brkt_sdk.egg-info/requires.txt
brkt_sdk.egg-info/top_level.txt
scripts/brkt_api_client