Metadata-Version: 1.0
Name: brkt_sdk
Version: 0.1
Summary: Python SDK to the Bracket API
Home-page: UNKNOWN
Author: UNKNOWN
Author-email: UNKNOWN
License: UNKNOWN
Platform: UNKNOWN
